_vovp.cpython-39-x86_64-linux-gnu.so
vovp/__init__.py
vovp/client.py
vovp/multiprocessing.py
vovp_lib/libarrow.so.300
vovp_lib/libarrow_cuda.so.300
vovp_lib/libplasma_client.so
vovp_lib/plasma-store-server
vovp_cuda-0.0.2.dist-info/LICENSE
vovp_cuda-0.0.2.dist-info/METADATA
vovp_cuda-0.0.2.dist-info/WHEEL
vovp_cuda-0.0.2.dist-info/top_level.txt
vovp_cuda-0.0.2.dist-info/RECORD
