Metadata-Version: 2.1
Name: vovp-cuda
Version: 0.0.2
Summary: KVStore for tensors
Home-page: UNKNOWN
Author: Allen Zhou
Author-email: UNKNOWN
License: UNKNOWN
Platform: UNKNOWN
